<?xml version="1.0" encoding="UTF-8"?>
<sv:node sv:name="ctSetup" xmlns:sv="http://www.jcp.org/jcr/sv/1.0" xmlns:xsi="http://www.w3.org/2001/XMLSchema-instance">
  <sv:property sv:name="jcr:primaryType" sv:type="Name">
    <sv:value>mgnl:contentNode</sv:value>
  </sv:property>
  <sv:property sv:name="jcr:uuid" sv:type="String">
    <sv:value>51380a6b-b2dc-a922-d572-c06bed18d593</sv:value>
  </sv:property>
  <sv:property sv:name="appClass" sv:type="String">
    <sv:value>info.magnolia.ui.framework.app.BaseApp</sv:value>
  </sv:property>
  <sv:property sv:name="class" sv:type="String">
    <sv:value>info.magnolia.ui.api.app.registry.ConfiguredAppDescriptor</sv:value>
  </sv:property>
  <sv:property sv:name="icon" sv:type="String">
    <sv:value>icon-configuration-app</sv:value>
  </sv:property>
  <sv:property sv:name="jcr:createdBy" sv:type="String">
    <sv:value>admin</sv:value>
  </sv:property>
  <sv:property sv:name="mgnl:created" sv:type="Date">
    <sv:value>2014-11-25T11:12:27.433+01:00</sv:value>
  </sv:property>
  <sv:property sv:name="mgnl:createdBy" sv:type="String">
    <sv:value>superuser</sv:value>
  </sv:property>
  <sv:property sv:name="mgnl:lastModified" sv:type="Date">
    <sv:value>2016-04-04T16:15:17.986+02:00</sv:value>
  </sv:property>
  <sv:property sv:name="mgnl:lastModifiedBy" sv:type="String">
    <sv:value>superuser</sv:value>
  </sv:property>
  <sv:property sv:name="name" sv:type="String">
    <sv:value>ctSetup</sv:value>
  </sv:property>
  <sv:node sv:name="subApps">
    <sv:property sv:name="jcr:primaryType" sv:type="Name">
      <sv:value>mgnl:contentNode</sv:value>
    </sv:property>
    <sv:property sv:name="jcr:uuid" sv:type="String">
      <sv:value>1518d9c5-dade-1e13-2b57-4d677390170b</sv:value>
    </sv:property>
    <sv:property sv:name="jcr:createdBy" sv:type="String">
      <sv:value>admin</sv:value>
    </sv:property>
    <sv:property sv:name="mgnl:created" sv:type="Date">
      <sv:value>2014-11-25T11:12:32.492+01:00</sv:value>
    </sv:property>
    <sv:property sv:name="mgnl:createdBy" sv:type="String">
      <sv:value>superuser</sv:value>
    </sv:property>
    <sv:property sv:name="mgnl:lastModified" sv:type="Date">
      <sv:value>2016-04-04T16:15:06.209+02:00</sv:value>
    </sv:property>
    <sv:property sv:name="mgnl:lastModifiedBy" sv:type="String">
      <sv:value>superuser</sv:value>
    </sv:property>
    <sv:node sv:name="main">
      <sv:property sv:name="jcr:primaryType" sv:type="Name">
        <sv:value>mgnl:contentNode</sv:value>
      </sv:property>
      <sv:property sv:name="jcr:uuid" sv:type="String">
        <sv:value>cfc91c30-63a6-28db-b77a-47ee741c08ca</sv:value>
      </sv:property>
      <sv:property sv:name="class" sv:type="String">
        <sv:value>info.magnolia.commercetools.integration.app.configuration.CommerceToolsConfigurationSubAppDescriptor</sv:value>
      </sv:property>
      <sv:property sv:name="closable" sv:type="String">
        <sv:value>false</sv:value>
      </sv:property>
      <sv:property sv:name="jcr:createdBy" sv:type="String">
        <sv:value>admin</sv:value>
      </sv:property>
      <sv:property sv:name="mgnl:created" sv:type="Date">
        <sv:value>2014-11-25T11:15:46.430+01:00</sv:value>
      </sv:property>
      <sv:property sv:name="mgnl:createdBy" sv:type="String">
        <sv:value>superuser</sv:value>
      </sv:property>
      <sv:property sv:name="mgnl:lastModified" sv:type="Date">
        <sv:value>2016-04-04T16:16:08.542+02:00</sv:value>
      </sv:property>
      <sv:property sv:name="mgnl:lastModifiedBy" sv:type="String">
        <sv:value>superuser</sv:value>
      </sv:property>
      <sv:property sv:name="subAppClass" sv:type="String">
        <sv:value>info.magnolia.commercetools.integration.app.configuration.CommerceToolsConfigurationSubApp</sv:value>
      </sv:property>
      <sv:node sv:name="formDefinition">
        <sv:property sv:name="jcr:primaryType" sv:type="Name">
          <sv:value>mgnl:contentNode</sv:value>
        </sv:property>
        <sv:property sv:name="jcr:uuid" sv:type="String">
          <sv:value>c81c081d-b968-bc51-1505-7fad571e8ffe</sv:value>
        </sv:property>
        <sv:property sv:name="jcr:createdBy" sv:type="String">
          <sv:value>admin</sv:value>
        </sv:property>
        <sv:property sv:name="mgnl:created" sv:type="Date">
          <sv:value>2014-11-25T12:28:11.162+01:00</sv:value>
        </sv:property>
        <sv:property sv:name="mgnl:createdBy" sv:type="String">
          <sv:value>superuser</sv:value>
        </sv:property>
        <sv:property sv:name="mgnl:lastModified" sv:type="Date">
          <sv:value>2016-04-04T16:15:06.209+02:00</sv:value>
        </sv:property>
        <sv:property sv:name="mgnl:lastModifiedBy" sv:type="String">
          <sv:value>superuser</sv:value>
        </sv:property>
        <sv:node sv:name="tabs">
          <sv:property sv:name="jcr:primaryType" sv:type="Name">
            <sv:value>mgnl:contentNode</sv:value>
          </sv:property>
          <sv:property sv:name="jcr:uuid" sv:type="String">
            <sv:value>1c06019f-171b-a43e-59a9-913958ac06ca</sv:value>
          </sv:property>
          <sv:property sv:name="jcr:createdBy" sv:type="String">
            <sv:value>admin</sv:value>
          </sv:property>
          <sv:property sv:name="mgnl:created" sv:type="Date">
            <sv:value>2014-11-25T12:28:36.581+01:00</sv:value>
          </sv:property>
          <sv:property sv:name="mgnl:createdBy" sv:type="String">
            <sv:value>superuser</sv:value>
          </sv:property>
          <sv:property sv:name="mgnl:lastModified" sv:type="Date">
            <sv:value>2016-04-04T16:15:06.209+02:00</sv:value>
          </sv:property>
          <sv:property sv:name="mgnl:lastModifiedBy" sv:type="String">
            <sv:value>superuser</sv:value>
          </sv:property>
          <sv:node sv:name="tabMain">
            <sv:property sv:name="jcr:primaryType" sv:type="Name">
              <sv:value>mgnl:contentNode</sv:value>
            </sv:property>
            <sv:property sv:name="jcr:uuid" sv:type="String">
              <sv:value>e598815f-0a20-59dd-135a-fef1cc78b442</sv:value>
            </sv:property>
            <sv:property sv:name="jcr:createdBy" sv:type="String">
              <sv:value>admin</sv:value>
            </sv:property>
            <sv:property sv:name="mgnl:created" sv:type="Date">
              <sv:value>2014-11-25T12:28:40.557+01:00</sv:value>
            </sv:property>
            <sv:property sv:name="mgnl:createdBy" sv:type="String">
              <sv:value>superuser</sv:value>
            </sv:property>
            <sv:property sv:name="mgnl:lastModified" sv:type="Date">
              <sv:value>2016-04-04T16:15:06.209+02:00</sv:value>
            </sv:property>
            <sv:property sv:name="mgnl:lastModifiedBy" sv:type="String">
              <sv:value>superuser</sv:value>
            </sv:property>
            <sv:node sv:name="fields">
              <sv:property sv:name="jcr:primaryType" sv:type="Name">
                <sv:value>mgnl:contentNode</sv:value>
              </sv:property>
              <sv:property sv:name="jcr:uuid" sv:type="String">
                <sv:value>a6a0bd5d-02b7-5a44-259b-8132200811ab</sv:value>
              </sv:property>
              <sv:property sv:name="jcr:createdBy" sv:type="String">
                <sv:value>admin</sv:value>
              </sv:property>
              <sv:property sv:name="mgnl:created" sv:type="Date">
                <sv:value>2014-11-25T12:28:46.793+01:00</sv:value>
              </sv:property>
              <sv:property sv:name="mgnl:createdBy" sv:type="String">
                <sv:value>superuser</sv:value>
              </sv:property>
              <sv:property sv:name="mgnl:lastModified" sv:type="Date">
                <sv:value>2016-04-04T16:15:06.209+02:00</sv:value>
              </sv:property>
              <sv:property sv:name="mgnl:lastModifiedBy" sv:type="String">
                <sv:value>superuser</sv:value>
              </sv:property>
              <sv:node sv:name="site">
                <sv:property sv:name="jcr:primaryType" sv:type="Name">
                  <sv:value>mgnl:contentNode</sv:value>
                </sv:property>
                <sv:property sv:name="jcr:uuid" sv:type="String">
                  <sv:value>69798771-cfb6-7e84-da27-b594899dfe63</sv:value>
                </sv:property>
                <sv:property sv:name="class" sv:type="String">
                  <sv:value>info.magnolia.commercetools.integration.app.configuration.field.SiteSelectFieldFactory$Definition</sv:value>
                </sv:property>
                <sv:property sv:name="jcr:createdBy" sv:type="String">
                  <sv:value>admin</sv:value>
                </sv:property>
                <sv:property sv:name="mgnl:created" sv:type="Date">
                  <sv:value>2014-11-25T14:41:56.552+01:00</sv:value>
                </sv:property>
                <sv:property sv:name="mgnl:createdBy" sv:type="String">
                  <sv:value>superuser</sv:value>
                </sv:property>
                <sv:property sv:name="mgnl:lastModified" sv:type="Date">
                  <sv:value>2016-04-06T13:11:03.455+02:00</sv:value>
                </sv:property>
                <sv:property sv:name="mgnl:lastModifiedBy" sv:type="String">
                  <sv:value>superuser</sv:value>
                </sv:property>
              </sv:node>
              <sv:node sv:name="ctProject">
                <sv:property sv:name="jcr:primaryType" sv:type="Name">
                  <sv:value>mgnl:contentNode</sv:value>
                </sv:property>
                <sv:property sv:name="jcr:uuid" sv:type="String">
                  <sv:value>04df66ca-c062-fb3b-035c-e6ea4cf55dcd</sv:value>
                </sv:property>
                <sv:property sv:name="class" sv:type="String">
                  <sv:value>info.magnolia.commercetools.integration.app.configuration.field.ProjectSelectFieldFactory$Definition</sv:value>
                </sv:property>
                <sv:property sv:name="jcr:createdBy" sv:type="String">
                  <sv:value>admin</sv:value>
                </sv:property>
                <sv:property sv:name="mgnl:activationStatus" sv:type="Boolean">
                  <sv:value>false</sv:value>
                </sv:property>
                <sv:property sv:name="mgnl:created" sv:type="Date">
                  <sv:value>2016-04-05T13:33:13.653+02:00</sv:value>
                </sv:property>
                <sv:property sv:name="mgnl:createdBy" sv:type="String">
                  <sv:value>superuser</sv:value>
                </sv:property>
                <sv:property sv:name="mgnl:lastActivated" sv:type="Date">
                  <sv:value>2016-04-05T13:33:13.659+02:00</sv:value>
                </sv:property>
                <sv:property sv:name="mgnl:lastActivatedBy" sv:type="String">
                  <sv:value>superuser</sv:value>
                </sv:property>
                <sv:property sv:name="mgnl:lastModified" sv:type="Date">
                  <sv:value>2016-04-07T10:39:37.533+02:00</sv:value>
                </sv:property>
                <sv:property sv:name="mgnl:lastModifiedBy" sv:type="String">
                  <sv:value>superuser</sv:value>
                </sv:property>
                <sv:property sv:name="required" sv:type="String">
                  <sv:value>true</sv:value>
                </sv:property>
                <sv:node sv:name="validators">
                  <sv:property sv:name="jcr:primaryType" sv:type="Name">
                    <sv:value>mgnl:contentNode</sv:value>
                  </sv:property>
                  <sv:property sv:name="jcr:uuid" sv:type="String">
                    <sv:value>2e988e36-2dd3-e597-c84e-e35601302a6b</sv:value>
                  </sv:property>
                  <sv:property sv:name="jcr:createdBy" sv:type="String">
                    <sv:value>admin</sv:value>
                  </sv:property>
                  <sv:property sv:name="mgnl:activationStatus" sv:type="Boolean">
                    <sv:value>false</sv:value>
                  </sv:property>
                  <sv:property sv:name="mgnl:created" sv:type="Date">
                    <sv:value>2016-04-06T16:47:04.595+02:00</sv:value>
                  </sv:property>
                  <sv:property sv:name="mgnl:createdBy" sv:type="String">
                    <sv:value>superuser</sv:value>
                  </sv:property>
                  <sv:property sv:name="mgnl:lastActivated" sv:type="Date">
                    <sv:value>2016-04-06T16:47:04.604+02:00</sv:value>
                  </sv:property>
                  <sv:property sv:name="mgnl:lastActivatedBy" sv:type="String">
                    <sv:value>superuser</sv:value>
                  </sv:property>
                  <sv:property sv:name="mgnl:lastModified" sv:type="Date">
                    <sv:value>2016-04-07T10:39:37.533+02:00</sv:value>
                  </sv:property>
                  <sv:property sv:name="mgnl:lastModifiedBy" sv:type="String">
                    <sv:value>superuser</sv:value>
                  </sv:property>
                  <sv:node sv:name="nonEmpty">
                    <sv:property sv:name="jcr:primaryType" sv:type="Name">
                      <sv:value>mgnl:contentNode</sv:value>
                    </sv:property>
                    <sv:property sv:name="jcr:uuid" sv:type="String">
                      <sv:value>0bee0883-bdcf-7309-bd0b-0a0cd0b1f18c</sv:value>
                    </sv:property>
                    <sv:property sv:name="class" sv:type="String">
                      <sv:value>info.magnolia.commercetools.integration.app.configuration.field.validator.NonEmptyValidatorDefinition</sv:value>
                    </sv:property>
                    <sv:property sv:name="jcr:createdBy" sv:type="String">
                      <sv:value>admin</sv:value>
                    </sv:property>
                    <sv:property sv:name="mgnl:activationStatus" sv:type="Boolean">
                      <sv:value>false</sv:value>
                    </sv:property>
                    <sv:property sv:name="mgnl:created" sv:type="Date">
                      <sv:value>2016-04-06T16:47:04.595+02:00</sv:value>
                    </sv:property>
                    <sv:property sv:name="mgnl:createdBy" sv:type="String">
                      <sv:value>superuser</sv:value>
                    </sv:property>
                    <sv:property sv:name="mgnl:lastActivated" sv:type="Date">
                      <sv:value>2016-04-06T16:47:04.605+02:00</sv:value>
                    </sv:property>
                    <sv:property sv:name="mgnl:lastActivatedBy" sv:type="String">
                      <sv:value>superuser</sv:value>
                    </sv:property>
                    <sv:property sv:name="mgnl:lastModified" sv:type="Date">
                      <sv:value>2016-04-07T10:39:37.533+02:00</sv:value>
                    </sv:property>
                    <sv:property sv:name="mgnl:lastModifiedBy" sv:type="String">
                      <sv:value>superuser</sv:value>
                    </sv:property>
                  </sv:node>
                </sv:node>
              </sv:node>
              <sv:node sv:name="ctLanguage">
                <sv:property sv:name="jcr:primaryType" sv:type="Name">
                  <sv:value>mgnl:contentNode</sv:value>
                </sv:property>
                <sv:property sv:name="jcr:uuid" sv:type="String">
                  <sv:value>2de09362-1629-30cc-8ba8-d1e4839cefbc</sv:value>
                </sv:property>
                <sv:property sv:name="class" sv:type="String">
                  <sv:value>info.magnolia.commercetools.integration.app.configuration.field.LanguageSelectFieldFactory$Definition</sv:value>
                </sv:property>
                <sv:property sv:name="jcr:createdBy" sv:type="String">
                  <sv:value>admin</sv:value>
                </sv:property>
                <sv:property sv:name="mgnl:activationStatus" sv:type="Boolean">
                  <sv:value>false</sv:value>
                </sv:property>
                <sv:property sv:name="mgnl:created" sv:type="Date">
                  <sv:value>2016-04-05T16:51:00.860+02:00</sv:value>
                </sv:property>
                <sv:property sv:name="mgnl:createdBy" sv:type="String">
                  <sv:value>superuser</sv:value>
                </sv:property>
                <sv:property sv:name="mgnl:lastActivated" sv:type="Date">
                  <sv:value>2016-04-05T16:51:00.863+02:00</sv:value>
                </sv:property>
                <sv:property sv:name="mgnl:lastActivatedBy" sv:type="String">
                  <sv:value>superuser</sv:value>
                </sv:property>
                <sv:property sv:name="mgnl:lastModified" sv:type="Date">
                  <sv:value>2016-04-07T10:39:41.665+02:00</sv:value>
                </sv:property>
                <sv:property sv:name="mgnl:lastModifiedBy" sv:type="String">
                  <sv:value>superuser</sv:value>
                </sv:property>
                <sv:property sv:name="required" sv:type="String">
                  <sv:value>true</sv:value>
                </sv:property>
                <sv:node sv:name="validators">
                  <sv:property sv:name="jcr:primaryType" sv:type="Name">
                    <sv:value>mgnl:contentNode</sv:value>
                  </sv:property>
                  <sv:property sv:name="jcr:uuid" sv:type="String">
                    <sv:value>05848a0f-f21d-48be-7276-03409506e3a6</sv:value>
                  </sv:property>
                  <sv:property sv:name="jcr:createdBy" sv:type="String">
                    <sv:value>admin</sv:value>
                  </sv:property>
                  <sv:property sv:name="mgnl:activationStatus" sv:type="Boolean">
                    <sv:value>false</sv:value>
                  </sv:property>
                  <sv:property sv:name="mgnl:created" sv:type="Date">
                    <sv:value>2016-04-06T16:46:44.925+02:00</sv:value>
                  </sv:property>
                  <sv:property sv:name="mgnl:createdBy" sv:type="String">
                    <sv:value>superuser</sv:value>
                  </sv:property>
                  <sv:property sv:name="mgnl:lastActivated" sv:type="Date">
                    <sv:value>2016-04-06T16:46:44.933+02:00</sv:value>
                  </sv:property>
                  <sv:property sv:name="mgnl:lastActivatedBy" sv:type="String">
                    <sv:value>superuser</sv:value>
                  </sv:property>
                  <sv:property sv:name="mgnl:lastModified" sv:type="Date">
                    <sv:value>2016-04-07T10:39:41.665+02:00</sv:value>
                  </sv:property>
                  <sv:property sv:name="mgnl:lastModifiedBy" sv:type="String">
                    <sv:value>superuser</sv:value>
                  </sv:property>
                  <sv:node sv:name="nonEmpty">
                    <sv:property sv:name="jcr:primaryType" sv:type="Name">
                      <sv:value>mgnl:contentNode</sv:value>
                    </sv:property>
                    <sv:property sv:name="jcr:uuid" sv:type="String">
                      <sv:value>474b916f-094a-119b-04cb-fe071dc63c04</sv:value>
                    </sv:property>
                    <sv:property sv:name="class" sv:type="String">
                      <sv:value>info.magnolia.commercetools.integration.app.configuration.field.validator.NonEmptyValidatorDefinition</sv:value>
                    </sv:property>
                    <sv:property sv:name="jcr:createdBy" sv:type="String">
                      <sv:value>admin</sv:value>
                    </sv:property>
                    <sv:property sv:name="mgnl:activationStatus" sv:type="Boolean">
                      <sv:value>false</sv:value>
                    </sv:property>
                    <sv:property sv:name="mgnl:created" sv:type="Date">
                      <sv:value>2016-04-06T16:46:44.925+02:00</sv:value>
                    </sv:property>
                    <sv:property sv:name="mgnl:createdBy" sv:type="String">
                      <sv:value>superuser</sv:value>
                    </sv:property>
                    <sv:property sv:name="mgnl:lastActivated" sv:type="Date">
                      <sv:value>2016-04-06T16:46:45.050+02:00</sv:value>
                    </sv:property>
                    <sv:property sv:name="mgnl:lastActivatedBy" sv:type="String">
                      <sv:value>superuser</sv:value>
                    </sv:property>
                    <sv:property sv:name="mgnl:lastModified" sv:type="Date">
                      <sv:value>2016-04-07T10:39:41.665+02:00</sv:value>
                    </sv:property>
                    <sv:property sv:name="mgnl:lastModifiedBy" sv:type="String">
                      <sv:value>superuser</sv:value>
                    </sv:property>
                  </sv:node>
                </sv:node>
              </sv:node>
              <sv:node sv:name="ctCountry">
                <sv:property sv:name="jcr:primaryType" sv:type="Name">
                  <sv:value>mgnl:contentNode</sv:value>
                </sv:property>
                <sv:property sv:name="jcr:uuid" sv:type="String">
                  <sv:value>29ec5f30-504c-840f-bdf2-8c91c973f4c4</sv:value>
                </sv:property>
                <sv:property sv:name="class" sv:type="String">
                  <sv:value>info.magnolia.commercetools.integration.app.configuration.field.CountrySelectFieldFactory$Definition</sv:value>
                </sv:property>
                <sv:property sv:name="jcr:createdBy" sv:type="String">
                  <sv:value>admin</sv:value>
                </sv:property>
                <sv:property sv:name="mgnl:activationStatus" sv:type="Boolean">
                  <sv:value>false</sv:value>
                </sv:property>
                <sv:property sv:name="mgnl:created" sv:type="Date">
                  <sv:value>2015-09-17T12:47:19.780+02:00</sv:value>
                </sv:property>
                <sv:property sv:name="mgnl:createdBy" sv:type="String">
                  <sv:value>superuser</sv:value>
                </sv:property>
                <sv:property sv:name="mgnl:lastActivated" sv:type="Date">
                  <sv:value>2015-09-17T12:47:19.780+02:00</sv:value>
                </sv:property>
                <sv:property sv:name="mgnl:lastActivatedBy" sv:type="String">
                  <sv:value>superuser</sv:value>
                </sv:property>
                <sv:property sv:name="mgnl:lastModified" sv:type="Date">
                  <sv:value>2016-04-07T10:39:46.607+02:00</sv:value>
                </sv:property>
                <sv:property sv:name="mgnl:lastModifiedBy" sv:type="String">
                  <sv:value>superuser</sv:value>
                </sv:property>
                <sv:property sv:name="required" sv:type="String">
                  <sv:value>true</sv:value>
                </sv:property>
                <sv:node sv:name="validators">
                  <sv:property sv:name="jcr:primaryType" sv:type="Name">
                    <sv:value>mgnl:contentNode</sv:value>
                  </sv:property>
                  <sv:property sv:name="jcr:uuid" sv:type="String">
                    <sv:value>95c18cf0-72b3-0047-16ad-2ae2813eeca0</sv:value>
                  </sv:property>
                  <sv:property sv:name="jcr:createdBy" sv:type="String">
                    <sv:value>admin</sv:value>
                  </sv:property>
                  <sv:property sv:name="mgnl:created" sv:type="Date">
                    <sv:value>2016-04-06T16:19:26.715+02:00</sv:value>
                  </sv:property>
                  <sv:property sv:name="mgnl:createdBy" sv:type="String">
                    <sv:value>superuser</sv:value>
                  </sv:property>
                  <sv:property sv:name="mgnl:lastModified" sv:type="Date">
                    <sv:value>2016-04-07T10:39:46.607+02:00</sv:value>
                  </sv:property>
                  <sv:property sv:name="mgnl:lastModifiedBy" sv:type="String">
                    <sv:value>superuser</sv:value>
                  </sv:property>
                  <sv:node sv:name="nonEmpty">
                    <sv:property sv:name="jcr:primaryType" sv:type="Name">
                      <sv:value>mgnl:contentNode</sv:value>
                    </sv:property>
                    <sv:property sv:name="jcr:uuid" sv:type="String">
                      <sv:value>5dfa5b6c-25ce-6230-3314-31f539167bf6</sv:value>
                    </sv:property>
                    <sv:property sv:name="class" sv:type="String">
                      <sv:value>info.magnolia.commercetools.integration.app.configuration.field.validator.NonEmptyValidatorDefinition</sv:value>
                    </sv:property>
                    <sv:property sv:name="jcr:createdBy" sv:type="String">
                      <sv:value>admin</sv:value>
                    </sv:property>
                    <sv:property sv:name="mgnl:created" sv:type="Date">
                      <sv:value>2016-04-06T16:19:40.429+02:00</sv:value>
                    </sv:property>
                    <sv:property sv:name="mgnl:createdBy" sv:type="String">
                      <sv:value>superuser</sv:value>
                    </sv:property>
                    <sv:property sv:name="mgnl:lastModified" sv:type="Date">
                      <sv:value>2016-04-07T10:39:46.607+02:00</sv:value>
                    </sv:property>
                    <sv:property sv:name="mgnl:lastModifiedBy" sv:type="String">
                      <sv:value>superuser</sv:value>
                    </sv:property>
                  </sv:node>
                </sv:node>
              </sv:node>
              <sv:node sv:name="ctCurrency">
                <sv:property sv:name="jcr:primaryType" sv:type="Name">
                  <sv:value>mgnl:contentNode</sv:value>
                </sv:property>
                <sv:property sv:name="jcr:uuid" sv:type="String">
                  <sv:value>206a2387-f7cb-0b9e-2751-fcb68ef36952</sv:value>
                </sv:property>
                <sv:property sv:name="class" sv:type="String">
                  <sv:value>info.magnolia.commercetools.integration.app.configuration.field.CurrencySelectFieldFactory$Definition</sv:value>
                </sv:property>
                <sv:property sv:name="jcr:createdBy" sv:type="String">
                  <sv:value>admin</sv:value>
                </sv:property>
                <sv:property sv:name="mgnl:activationStatus" sv:type="Boolean">
                  <sv:value>false</sv:value>
                </sv:property>
                <sv:property sv:name="mgnl:created" sv:type="Date">
                  <sv:value>2016-04-05T16:50:50.378+02:00</sv:value>
                </sv:property>
                <sv:property sv:name="mgnl:createdBy" sv:type="String">
                  <sv:value>superuser</sv:value>
                </sv:property>
                <sv:property sv:name="mgnl:lastActivated" sv:type="Date">
                  <sv:value>2016-04-05T16:50:50.381+02:00</sv:value>
                </sv:property>
                <sv:property sv:name="mgnl:lastActivatedBy" sv:type="String">
                  <sv:value>superuser</sv:value>
                </sv:property>
                <sv:property sv:name="mgnl:lastModified" sv:type="Date">
                  <sv:value>2016-04-07T10:39:50.991+02:00</sv:value>
                </sv:property>
                <sv:property sv:name="mgnl:lastModifiedBy" sv:type="String">
                  <sv:value>superuser</sv:value>
                </sv:property>
                <sv:property sv:name="required" sv:type="String">
                  <sv:value>true</sv:value>
                </sv:property>
                <sv:node sv:name="validators">
                  <sv:property sv:name="jcr:primaryType" sv:type="Name">
                    <sv:value>mgnl:contentNode</sv:value>
                  </sv:property>
                  <sv:property sv:name="jcr:uuid" sv:type="String">
                    <sv:value>abc50cc5-9ad0-b02e-c481-8a8d31533349</sv:value>
                  </sv:property>
                  <sv:property sv:name="jcr:createdBy" sv:type="String">
                    <sv:value>admin</sv:value>
                  </sv:property>
                  <sv:property sv:name="mgnl:activationStatus" sv:type="Boolean">
                    <sv:value>false</sv:value>
                  </sv:property>
                  <sv:property sv:name="mgnl:created" sv:type="Date">
                    <sv:value>2016-04-06T16:47:24.136+02:00</sv:value>
                  </sv:property>
                  <sv:property sv:name="mgnl:createdBy" sv:type="String">
                    <sv:value>superuser</sv:value>
                  </sv:property>
                  <sv:property sv:name="mgnl:lastActivated" sv:type="Date">
                    <sv:value>2016-04-06T16:47:24.139+02:00</sv:value>
                  </sv:property>
                  <sv:property sv:name="mgnl:lastActivatedBy" sv:type="String">
                    <sv:value>superuser</sv:value>
                  </sv:property>
                  <sv:property sv:name="mgnl:lastModified" sv:type="Date">
                    <sv:value>2016-04-07T10:39:50.991+02:00</sv:value>
                  </sv:property>
                  <sv:property sv:name="mgnl:lastModifiedBy" sv:type="String">
                    <sv:value>superuser</sv:value>
                  </sv:property>
                  <sv:node sv:name="nonEmpty">
                    <sv:property sv:name="jcr:primaryType" sv:type="Name">
                      <sv:value>mgnl:contentNode</sv:value>
                    </sv:property>
                    <sv:property sv:name="jcr:uuid" sv:type="String">
                      <sv:value>3e161e3b-e694-22ab-cd73-a4c53a39c7c0</sv:value>
                    </sv:property>
                    <sv:property sv:name="class" sv:type="String">
                      <sv:value>info.magnolia.commercetools.integration.app.configuration.field.validator.NonEmptyValidatorDefinition</sv:value>
                    </sv:property>
                    <sv:property sv:name="jcr:createdBy" sv:type="String">
                      <sv:value>admin</sv:value>
                    </sv:property>
                    <sv:property sv:name="mgnl:activationStatus" sv:type="Boolean">
                      <sv:value>false</sv:value>
                    </sv:property>
                    <sv:property sv:name="mgnl:created" sv:type="Date">
                      <sv:value>2016-04-06T16:47:24.136+02:00</sv:value>
                    </sv:property>
                    <sv:property sv:name="mgnl:createdBy" sv:type="String">
                      <sv:value>superuser</sv:value>
                    </sv:property>
                    <sv:property sv:name="mgnl:lastActivated" sv:type="Date">
                      <sv:value>2016-04-06T16:47:24.145+02:00</sv:value>
                    </sv:property>
                    <sv:property sv:name="mgnl:lastActivatedBy" sv:type="String">
                      <sv:value>superuser</sv:value>
                    </sv:property>
                    <sv:property sv:name="mgnl:lastModified" sv:type="Date">
                      <sv:value>2016-04-07T10:39:50.991+02:00</sv:value>
                    </sv:property>
                    <sv:property sv:name="mgnl:lastModifiedBy" sv:type="String">
                      <sv:value>superuser</sv:value>
                    </sv:property>
                  </sv:node>
                </sv:node>
              </sv:node>
            </sv:node>
          </sv:node>
        </sv:node>
      </sv:node>
    </sv:node>
  </sv:node>
</sv:node>
